panthon/__init__.py
panthon/arp_spoofing.py
panthon/ddos_attack.py
panthon/dns_spoofer.py
panthon/dos_attack.py
panthon/mitm_attack.py
panthon/network_spoofer.py
panthon/sql_injection.py
panthon/website_extractor.py
panthon/xss_attack.py
panthon/DDOS/saphyra.py
panthon/DDOS/aSYNcrone/aSYNcrone
panthon/DDOS/aSYNcrone/aSYNcrone-macARM.c
panthon/DDOS/aSYNcrone/aSYNcrone.c
panthon/DDOS/aSYNcrone/aSYNcronemacARM
panthon/DDOS/aSYNcrone/src/random-ip-macARM.c
panthon/DDOS/aSYNcrone/src/random-ip.c
panthon/DDOS/aSYNcrone/src/tanitim.c
panthon/DOS/goldeneye.py
panthon/SQL/__init__.py
panthon/SQL/dsss.py
panthon/SQL/sqlmap/README.md
panthon/SQL/sqlmap/sqlmap.conf
panthon/SQL/sqlmap/sqlmap.py
panthon/SQL/sqlmap/sqlmapapi.py
panthon/SQL/sqlmap/sqlmapapi.yaml
panthon/SQL/sqlmap/data/html/index.html
panthon/SQL/sqlmap/data/procs/README.txt
panthon/SQL/sqlmap/data/procs/mssqlserver/activate_sp_oacreate.sql
panthon/SQL/sqlmap/data/procs/mssqlserver/configure_openrowset.sql
panthon/SQL/sqlmap/data/procs/mssqlserver/configure_xp_cmdshell.sql
panthon/SQL/sqlmap/data/procs/mssqlserver/create_new_xp_cmdshell.sql
panthon/SQL/sqlmap/data/procs/mssqlserver/disable_xp_cmdshell_2000.sql
panthon/SQL/sqlmap/data/procs/mssqlserver/dns_request.sql
panthon/SQL/sqlmap/data/procs/mssqlserver/enable_xp_cmdshell_2000.sql
panthon/SQL/sqlmap/data/procs/mssqlserver/run_statement_as_user.sql
panthon/SQL/sqlmap/data/procs/mysql/dns_request.sql
panthon/SQL/sqlmap/data/procs/mysql/write_file_limit.sql
panthon/SQL/sqlmap/data/procs/oracle/dns_request.sql
panthon/SQL/sqlmap/data/procs/oracle/read_file_export_extension.sql
panthon/SQL/sqlmap/data/procs/postgresql/dns_request.sql
panthon/SQL/sqlmap/data/shell/README.txt
panthon/SQL/sqlmap/data/shell/backdoors/backdoor.asp_
panthon/SQL/sqlmap/data/shell/backdoors/backdoor.aspx_
panthon/SQL/sqlmap/data/shell/backdoors/backdoor.jsp_
panthon/SQL/sqlmap/data/shell/backdoors/backdoor.php_
panthon/SQL/sqlmap/data/shell/stagers/stager.asp_
panthon-0.3.0.dist-info/LICENSE
panthon-0.3.0.dist-info/METADATA
panthon-0.3.0.dist-info/WHEEL
panthon-0.3.0.dist-info/top_level.txt
panthon-0.3.0.dist-info/RECORD
