Metadata-Version: 2.1
Name: panthon
Version: 0.3.0
Summary: Panthon employs sophisticated methods to replicate different cyber threats, offering a dynamic solution to proactively address the constantly shifting realm of cybersecurity risks. Our goal is to help build more resilient and secure systems through a deeper understanding and anticipation of potential vulnerabilities.
Author: Nripesh
Author-email: Nripesh14@gmail.com
License: Apache Software License
Classifier: License :: OSI Approved :: Apache Software License
License-File: LICENSE
Requires-Dist: scapy
Requires-Dist: netifaces
Requires-Dist: bs4
Requires-Dist: tld
Requires-Dist: fuzzywuzzy
Requires-Dist: requests
Requires-Dist: twisted
Requires-Dist: lxml
